{"notifynum":"8","productsNo":"100079633001","tag":"killpro","displaytag":"sale","deatilpics":[{"orderindex":null,"img":"http://cdnec.sasa.com/public/promoImgs/productgallery/100079633001_01.jpg?1429068691#w","imgHight":"0","imgWidth":"0","type":"实拍图"},{"orderindex":null,"img":"http://cdnec.sasa.com/public/promoImgs/productgallery/100079633001_02.jpg?1429068691#w","imgHight":"0","imgWidth":"0","type":"实拍图"},{"orderindex":null,"img":"http://cdnec.sasa.com/public/promoImgs/productgallery/100079633001_03.jpg?1429068691#w","imgHight":"0","imgWidth":"0","type":"实拍图"},{"orderindex":null,"img":"http://cdnec.sasa.com/public/promoImgs/productgallery/100079633001_04.jpg?1429068691#w","imgHight":"0","imgWidth":"0","type":"实拍图"},{"orderindex":null,"img":"http://cdnec.sasa.com/public/promoImgs/productgallery/100079633001_05.jpg?1429068691#w","imgHight":"0","imgWidth":"0","type":"实拍图"}],"img":"public/images/19/1b/91/af53c5fa677979ff657dcf0503bf42e61916bf78.jpg","retailPrice":"560.000000","isnewhome":"0","stock":"684","seckill_id":"89338","producttagtype":[{"tagfilter":"b2c_brand_origin_tag_jp","tagtype":"brand","img":"public/images/4b/c4/be/658eaaa004abf71273aa72856b3b9430e875f4d1.png","producttagid":"28","producttagname":"日本品牌"},{"tagfilter":"tags_tag_review","tagtype":"goods","img":"public/images/2a/0f/0a/927b1d631101309f5b7290337c803b4f1bca2fcb.png","producttagid":"13","producttagname":"好评中"},{"tagfilter":"tags_tag_new","tagtype":"goods","img":"public/images/bc/98/2c/1982aa26b2de9ef8efcc6248b73272e962714eaa.png","producttagid":"12","producttagname":"新品上市"},{"tagfilter":"tags_tag_hot","tagtype":"goods","img":"public/images/96/12/dd/45d954f097d557085ffa9cb3110cf5d753118162.png","producttagid":"11","producttagname":"热卖中"},{"tagfilter":"tags_tag_origin","tagtype":"goods","img":"public/images/18/8f/31/f038fa6b27b7c00232bc29080702470342f318ad.png","producttagid":"206","producttagname":"日本制造"}],"isnew":"0","pricespec":[{"META_SIZE":"360毫升","META_SIZE_CODE":"abc"}],"starttime":"2016-10-10 09:00:00.0","forapp":"0","storeNameId":"4952dfbf-b2b5-4cb5-8779-e11e431f4d06","dowmprice":"","efficacy":[],"disnumber":"0","like":"72936","comprice":"0","storeNameEn":"Kose Medicated Sekkisei","discount":"5.7折","price":"319.00","priceMapping":[{"endtime":"2016-10-11 08:59:59.0","META_SIZE":"360毫升","tag":"killpro","bn":"100079633001","salePurchase":"36","isOnlineExclusive":"","META_SIZE_CODE":null,"stock":"433","producttagtype":null,"seckill_id":"89338","isnew":"0","is_bonded":"false","oldprice":"560.00","storeid":"4952dfbf-b2b5-4cb5-8779-e11e431f4d06","ecstoreId":"2018","forapp":"0","dowmprice":null,"META_COLOR":"FREE","pid":"dfa12f92-a0d7-4db2-ab6a-5741cf53c664","storetype":null,"discount":"5.7折","productId":"1bacfc4d-01c9-4588-8860-f036e18a255a","viplvprice":"","price":"319.00","goodsid":"2749","nums":"684","pname":"雪肌精 化妆水 (360毫升)","META_COLOR_CODE":null,"salePlayCount":"23","pricemappingstock":"433"}],"secondCategory":"13143883-df8c-49d3-8d7e-4d96d94c5a28","salePlayCount":"23","topCategory":"716f8a75-8121-42f3-b695-c208604edc64","endtime":"2016-10-11 08:59:59.0","desc":"<table border=\"0\"><tbody><tr><td><img style=\"width: 100%\" style=\"width: 100%\" style=\"width: 100%\" style=\"width: 100%\" style=\"width: 100%\" style=\"width: 100%\" style=\"width: 100%\" style=\"width: 100%\" style=\"width: 100%\" style=\"width: 100%\" style=\"width: 100%\" style=\"width: 100%\" style=\"width: 100%\" border=\"0\" alt=\"\" src=\"http://cdnec.sasa.com/public/promoImgs/productdetails/100079633001_a.jpg\" style=\"float: left;\"><br/><img style=\"width: 100%\" style=\"width: 100%\" style=\"width: 100%\" style=\"width: 100%\" style=\"width: 100%\" style=\"width: 100%\" style=\"width: 100%\" style=\"width: 100%\" style=\"width: 100%\" style=\"width: 100%\" style=\"width: 100%\" style=\"width: 100%\" style=\"width: 100%\" border=\"0\" alt=\"\" src=\"http://cdnec.sasa.com/public/promoImgs/productdetails/100079633001_b.jpg\" style=\"float: left;\"><br/><img style=\"width: 100%\" style=\"width: 100%\" style=\"width: 100%\" style=\"width: 100%\" style=\"width: 100%\" style=\"width: 100%\" style=\"width: 100%\" style=\"width: 100%\" style=\"width: 100%\" style=\"width: 100%\" style=\"width: 100%\" style=\"width: 100%\" style=\"width: 100%\" border=\"0\" alt=\"\" src=\"http://cdnec.sasa.com/public/promoImgs/productdetails/100079633001_c.jpg\" style=\"float: left;\"><br/><img style=\"width: 100%\" style=\"width: 100%\" style=\"width: 100%\" style=\"width: 100%\" style=\"width: 100%\" style=\"width: 100%\" style=\"width: 100%\" style=\"width: 100%\" style=\"width: 100%\" style=\"width: 100%\" style=\"width: 100%\" style=\"width: 100%\" style=\"width: 100%\" border=\"0\" alt=\"\" src=\"http://cdnec.sasa.com/public/promoImgs/productdetails/100079633001_d.jpg\" style=\"float: left;\"><br/><img style=\"width: 100%\" style=\"width: 100%\" style=\"width: 100%\" style=\"width: 100%\" style=\"width: 100%\" style=\"width: 100%\" style=\"width: 100%\" style=\"width: 100%\" style=\"width: 100%\" style=\"width: 100%\" style=\"width: 100%\" style=\"width: 100%\" style=\"width: 100%\" border=\"0\" alt=\"\" src=\"http://cdnec.sasa.com/public/promoImgs/productdetails/100079633001_e.jpg\" style=\"float: left;\"><\/td><\/tr><\/tbody><\/table><strong><使用方法><\/strong><br/><br/><img style=\"width: 100%\" style=\"width: 100%\" style=\"width: 100%\" style=\"width: 100%\" style=\"width: 100%\" style=\"width: 100%\" style=\"width: 100%\" style=\"width: 100%\" style=\"width: 100%\" style=\"width: 100%\" style=\"width: 100%\" style=\"width: 100%\" style=\"width: 100%\" alt=\"\" src=\"http://cdnec.sasa.com/public/promoImgs/howtouse/13_toner.jpg\" border=\"0\">","attribute":[{"alias":"productNoC","name":"商品编号","value":"100079633001","size":""},{"alias":"productBrandC","name":"商品品牌","value":"Kose Medicated Sekkisei","size":""},{"alias":"productNameC","name":"商品名称","value":"化妆水","size":""},{"alias":"productEfficacyC","name":"商品功效","value":"保湿,滋润,美白,提亮肤色,提拉紧致,抗皱/去皱","size":""},{"alias":"productSpecC","name":"商品规格","value":"360毫升","size":""},{"alias":"shelfLifeC","name":"保质期限","value":"3年，具体日期以收到的实物为准，开封后跟产品包装指示为准","size":""},{"alias":"countryOfOriginC","name":"原产国家","value":"日本","size":""},{"alias":"适用人群","name":"适用人群","value":"所有肌肤","size":""}],"lian":{"iffollow":"0","sgrade":"0","fans":"0","relationpost":null,"datarealtion":null,"sicon":"","sname":"雪肌精","storedesc":"","discuss":null,"likepeople":null,"dataother":null,"newproductnum":"0","sbackground":"","productnum":"24"},"id":"dfa12f92-a0d7-4db2-ab6a-5741cf53c664","salePurchase":"36","pics":[{"orderindex":null,"img":"public/images/19/1b/91/af53c5fa677979ff657dcf0503bf42e61916bf78.jpg","imgHight":"0","imgWidth":"0","type":"main"},{"orderindex":null,"img":"public/images/61/2b/14/b7767383d3f5dfb90e138bcd5a49637a2bfb5955.jpg","imgHight":"0","imgWidth":"0","type":"main"},{"orderindex":null,"img":"public/images/0b/bc/e5/255db804d698dca545110ff22a9554d14fcff8e7.jpg","imgHight":"0","imgWidth":"0","type":"main"},{"orderindex":null,"img":"public/images/14/cb/89/a4e8e449871946887d6314f3d3b45bd12eed53ee.jpg","imgHight":"0","imgWidth":"0","type":"main"},{"orderindex":null,"img":"public/images/1f/67/dc/2570992a07d126270673b426319390efad3320c2.jpg","imgHight":"0","imgWidth":"0","type":"main"}],"isOnlineExclusive":"false","name":"雪肌精 化妆水 (360毫升)","imgHight":0,"is_bonded":"false","oldPrice":"560.00","salesprice":"319.00","storeName":"雪肌精","supplier_id":"","islike":"0","ecstoreId":"2749","paycount":"10644","imgWidth":0,"storetype":"7","viplvprice":"","avgscore":"","nums":"684","productTitle":"台湾人气时尚彩妆保养杂志《BEAUTY美人志》强力推荐。用中日多种植物精华液配制，感触清新凉爽，充分润泽，修复粗糙无光的肌肤纹理。","comrate":"0"}