{"notifynum":"148","productsNo":"105567306001","tag":"downpro","displaytag":"product","img":"public/images/4b/61/03/538849090ebdcf82c133cf2972d075b136d8cde9.jpg","retailPrice":"210.000000","isnewhome":"0","stock":"184","seckill_id":"","producttagtype":[{"tagfilter":"tags_tag_new","tagtype":"goods","img":"public/images/bc/98/2c/1982aa26b2de9ef8efcc6248b73272e962714eaa.png","producttagid":"12","producttagname":"新品上市"},{"tagfilter":"tags_tag_origin","tagtype":"goods","img":"public/images/3c/85/7b/567ab877983664889cf5090e2e5764e6c6f4e3f5.png","producttagid":"216","producttagname":"美国制造"},{"tagfilter":"tags_tag_hot","tagtype":"goods","img":"public/images/96/12/dd/45d954f097d557085ffa9cb3110cf5d753118162.png","producttagid":"11","producttagname":"热卖中"},{"tagfilter":"tags_tag_review","tagtype":"goods","img":"public/images/2a/0f/0a/927b1d631101309f5b7290337c803b4f1bca2fcb.png","producttagid":"13","producttagname":"好评中"},{"tagfilter":"b2c_brand_origin_tag_ea","tagtype":"brand","img":"public/images/d7/ee/27/2d54e4c0f0e220f3cabe91e71562545a50b01308.png","producttagid":"30","producttagname":"欧美品牌"}],"isnew":"0","pricespec":[{"META_SIZE":"250毫升","META_SIZE_CODE":"Kiehls TONER Ultra Facial Toner"}],"starttime":"","forapp":"0","storeNameId":"43216e20-1d0c-4832-93ff-c2527f843d84","dowmprice":"165.000000","efficacy":[],"disnumber":"0","like":"44462","comprice":"0","storeNameEn":"Kiehls","discount":"7.9折","price":"165.000000","priceMapping":[{"endtime":"","META_SIZE":"250毫升","tag":"downpro","bn":"105567306001","salePurchase":"","isOnlineExclusive":"","META_SIZE_CODE":"Kiehls TONER Ultra Facial Toner","stock":"184","producttagtype":null,"seckill_id":"","isnew":"0","is_bonded":"false","oldprice":"210.00","storeid":"43216e20-1d0c-4832-93ff-c2527f843d84","ecstoreId":"12225","forapp":"0","dowmprice":"165.000000","META_COLOR":"FREE","pid":"283adbf9-d17a-4438-b44b-470fbe5fa239","storetype":null,"discount":"7.9折","productId":"4fbbc32d-ccff-4c29-a055-519da1ad3ac6","viplvprice":"","price":"165.000000","goodsid":"12963","nums":"","pname":"科颜氏 高保湿系列 高保湿精华爽肤水 (250毫升)","META_COLOR_CODE":null,"salePlayCount":"","pricemappingstock":"184"}],"secondCategory":"13143883-df8c-49d3-8d7e-4d96d94c5a28","salePlayCount":"","topCategory":"716f8a75-8121-42f3-b695-c208604edc64","endtime":"","desc":"<strong><產品介紹><\/strong><br/><br/><契尔氏( Kiehl's)高保湿精华爽肤水固名思义，是一瓶具特级保湿功效的之妆水！其独特的乳状结构，能呵护肌肤，维持皮肤天然的酸碱平衡，保护功能温和的高机能保湿化妆水，经乳化配方制成独特的乳状结构能高效保湿。不含酒精的非收敛配方能补充肌肤水分，同时轻柔除去皮肤上的尘垢及残留物，维持皮肤天然的屏障功能，保持皮肤的酸碱平衡。更可使用于肌肤极度干燥或过敏时做为急救补充水份湿敷使用，让你随时光采动人。 KIEHL´S凭借150多年的医药专业与草本知识，和顶尖皮肤科医师以及科学家共同合作，发展出最天然、安全且有效的保养品。能有效解决提早老化、刺激发炎和敏感性肌肤等症状。><br/><● 自1970年推出以来，即不限男女、适用于各肤质的热卖品><br/><● 作为一款高机能保湿爽肤水，温和舒缓肌肤、及时给肌肤补充水份><br/><● 蕴含的角鲨烷是高度精炼的保湿油，与皮肤的天然油份极其相容，吸收力强且柔软><br/><● 富含杏核油、牛油果油及甜杏仁油等滋润成分，使皮肤柔嫩保湿同时帮助肌肤保持透亮与细致。><br/><br/><br/><br/><strong><使用方法><\/strong><br/><br/><img style=\"width: 100%\" style=\"width: 100%\" style=\"width: 100%\" alt=\"\" src=\"http://cdnec.sasa.com/public/promoImgs/howtouse/13_toner.jpg\" border=\"0\"><br/><br/><strong><成份><\/strong><br/><br/><1. 杏仁油 杏仁油用杏仁提炼而成，蕴含大量维生素E（可加速脂肪吸收）。它是一种甘油三酸酯，含有75%的油酸、20%的亚油酸以及不饱和脂肪酸甘油脂 - 类似鳄梨油和芝麻油。 人们发现它具有高度的亲肤性。 杏仁油可使肌肤润泽光滑，亮丽柔软。 2.牛油果油 牛油果油用美洲热带牛油果树的果实提炼而成，是一种饱含脂肪酸的润滑剂，在所有的果油中保湿功能最强。它也是自然界中氨基酸蛋白、维生素A、D、E及钠元素的来源之一。有助于恢复肌肤的天然保湿功能。 3.角鲨烷（又称Perhydrosqualene或perhydrosqualene vegetal） 角鲨烷是用橄榄制成的一种质地极为细腻的保湿油；质地如丝般光滑，容易吸收，可与人体自身油脂轻松融合；科颜氏众多产品中均添加了角鲨烷。>","attribute":[{"alias":"productNoC","name":"商品编号","value":"105567306001","size":""},{"alias":"productBrandC","name":"商品品牌","value":"Kiehls","size":""},{"alias":"productSerieC","name":"商品系列","value":"高保湿系列","size":""},{"alias":"productNameC","name":"商品名称","value":"高保湿精华爽肤水","size":""},{"alias":"productSpecC","name":"商品规格","value":"250毫升","size":""},{"alias":"shelfLifeC","name":"保质期限","value":"3年，具体日期以收到的实物为准，开封后跟产品包装指示为准","size":""},{"alias":"countryOfOriginC","name":"原产国家","value":"美国","size":""}],"lian":{"iffollow":"0","sgrade":"0","fans":"0","relationpost":null,"datarealtion":null,"sicon":"","sname":"科颜氏","storedesc":"","discuss":null,"likepeople":null,"dataother":null,"newproductnum":"0","sbackground":"","productnum":"44"},"id":"283adbf9-d17a-4438-b44b-470fbe5fa239","salePurchase":"","pics":[{"orderindex":null,"img":"public/images/4b/61/03/538849090ebdcf82c133cf2972d075b136d8cde9.jpg","imgHight":"0","imgWidth":"0","type":"main"}],"isOnlineExclusive":"false","name":"科颜氏 高保湿系列 高保湿精华爽肤水 (250毫升)","imgHight":0,"is_bonded":"false","oldPrice":"210.00","salesprice":"0","storeName":"科颜氏","supplier_id":"","islike":"0","ecstoreId":"12963","paycount":"2149","imgWidth":0,"storetype":"7","viplvprice":"","avgscore":"","color":[{"keyName":"META_SIZE","name":"规格","value":[{"specName":"250毫升","sysImg":null,"pimg":"public/images/4b/61/03/538849090ebdcf82c133cf2972d075b136d8cde9.jpg"}],"fieldname":"META_SIZE"}],"nums":"0","productTitle":"其独特的乳状结构，能呵护肌肤，维持皮肤天然的酸碱平衡，保护功能温和的高机能保湿化妆水，经乳化配方制成独特的乳状结构能高效保湿。","comrate":"0"}